github_action_toolkit/__init__.py
github_action_toolkit/consts.py
github_action_toolkit/debugging.py
github_action_toolkit/event_models.py
github_action_toolkit/event_payload.py
github_action_toolkit/exceptions.py
github_action_toolkit/git_manager.py
github_action_toolkit/github_api_client.py
github_action_toolkit/github_artifacts.py
github_action_toolkit/github_cache.py
github_action_toolkit/input_output.py
github_action_toolkit/job_summary.py
github_action_toolkit/local_simulator.py
github_action_toolkit/print_messages.py
github_action_toolkit/py.typed
github_action_toolkit/signal_handling.py
github_action_toolkit/version.py
github_action_toolkit-0.8.0.dist-info/METADATA
github_action_toolkit-0.8.0.dist-info/WHEEL
github_action_toolkit-0.8.0.dist-info/entry_points.txt
github_action_toolkit-0.8.0.dist-info/licenses/LICENSE
github_action_toolkit-0.8.0.dist-info/RECORD
