Metadata-Version: 2.4
Name: github-action-toolkit
Version: 0.8.0
Summary: A Python library for utility functions and class helpful for custom GitHub actions.
Project-URL: Repository, https://github.com/VatsalJagani/github-action-toolkit
Project-URL: Homepage, https://github.com/VatsalJagani/github-action-toolkit-python
Project-URL: Documentation, https://github-action-toolkit.readthedocs.io/
Project-URL: Changelog, https://github.com/VatsalJagani/github-action-toolkit-python/blob/main/CHANGELOG.md
Author-email: Vatsal Jagani <vatsaljagani85@gmail.com>
License:                                  Apache License
License-File: LICENSE
Classifier: Development Status :: 4 - Beta
Classifier: Intended Audience :: Developers
Classifier: License :: OSI Approved :: Apache Software License
Classifier: Operating System :: OS Independent
Classifier: Programming Language :: Python
Classifier: Programming Language :: Python :: 3
Classifier: Programming Language :: Python :: 3 :: Only
Classifier: Programming Language :: Python :: 3.11
Classifier: Programming Language :: Python :: 3.12
Classifier: Programming Language :: Python :: 3.13
Classifier: Topic :: Software Development :: Libraries :: Python Modules
Classifier: Topic :: Software Development :: Version Control :: Git
Classifier: Topic :: Utilities
Classifier: Typing :: Typed
Requires-Python: <4.0,>=3.11
Requires-Dist: gitpython>=3.1
Requires-Dist: pydantic>=2.0
Requires-Dist: pygithub>=1.58
Provides-Extra: dev
Requires-Dist: basedpyright>=1.29.1; extra == 'dev'
Requires-Dist: codespell>=2.4.1; extra == 'dev'
Requires-Dist: funlog>=0.2.1; extra == 'dev'
Requires-Dist: furo>=2025.9.25; extra == 'dev'
Requires-Dist: hypothesis>=6.122.3; extra == 'dev'
Requires-Dist: mypy>=1.15.0; extra == 'dev'
Requires-Dist: myst-parser>=4.0.1; extra == 'dev'
Requires-Dist: pip>=25.2; extra == 'dev'
Requires-Dist: pytest-cov>=7.0.0; extra == 'dev'
Requires-Dist: pytest-sugar>=1.0.0; extra == 'dev'
Requires-Dist: pytest>=8.3.5; extra == 'dev'
Requires-Dist: rich>=14.0.0; extra == 'dev'
Requires-Dist: ruff>=0.11.9; extra == 'dev'
Requires-Dist: sphinx-autobuild>=2025.8.25; extra == 'dev'
Requires-Dist: sphinx-autodoc-typehints>=3.4.0; extra == 'dev'
Requires-Dist: sphinx-copybutton>=0.5.2; extra == 'dev'
Requires-Dist: sphinx>=8.2.3; extra == 'dev'
Requires-Dist: syrupy>=4.9.0; extra == 'dev'
Requires-Dist: twine>=6.2.0; extra == 'dev'
Requires-Dist: types-requests>=2.31.0; extra == 'dev'
Provides-Extra: docs
Requires-Dist: furo>=2025.9.25; extra == 'docs'
Requires-Dist: myst-parser>=4.0.1; extra == 'docs'
Requires-Dist: sphinx-autobuild>=2025.8.25; extra == 'docs'
Requires-Dist: sphinx-autodoc-typehints>=3.4.0; extra == 'docs'
Requires-Dist: sphinx-copybutton>=0.5.2; extra == 'docs'
Requires-Dist: sphinx>=8.2.3; extra == 'docs'
Provides-Extra: lint
Requires-Dist: codespell>=2.4.1; extra == 'lint'
Requires-Dist: ruff>=0.11.9; extra == 'lint'
Provides-Extra: release
Requires-Dist: pip>=25.2; extra == 'release'
Requires-Dist: twine>=6.2.0; extra == 'release'
Provides-Extra: test
Requires-Dist: hypothesis>=6.122.3; extra == 'test'
Requires-Dist: pytest-cov>=7.0.0; extra == 'test'
Requires-Dist: pytest-sugar>=1.0.0; extra == 'test'
Requires-Dist: pytest>=8.3.5; extra == 'test'
Requires-Dist: syrupy>=4.9.0; extra == 'test'
Provides-Extra: typing
Requires-Dist: basedpyright>=1.29.1; extra == 'typing'
Requires-Dist: mypy>=1.15.0; extra == 'typing'
Requires-Dist: types-requests>=2.31.0; extra == 'typing'
Provides-Extra: utils
Requires-Dist: funlog>=0.2.1; extra == 'utils'
Requires-Dist: rich>=14.0.0; extra == 'utils'
